randwords/__init__.py
randwords/entropy.py
randwords/words
randwords/cmd/__init__.py
randwords/cmd/randstring.py
randwords/cmd/randwords.py
randwords/tests/__init__.py
randwords/tests/test_entropy.py
randwords-1.1.2.dist-info/AUTHORS
randwords-1.1.2.dist-info/LICENSE
randwords-1.1.2.dist-info/METADATA
randwords-1.1.2.dist-info/WHEEL
randwords-1.1.2.dist-info/entry_points.txt
randwords-1.1.2.dist-info/top_level.txt
randwords-1.1.2.dist-info/RECORD
