Metadata-Version: 2.1
Name: randwords
Version: 1.1.2
Summary: Utilities to generate random words and strings
Classifier: Development Status :: 4 - Beta
Classifier: Environment :: Console
Classifier: Intended Audience :: End Users/Desktop
Classifier: Intended Audience :: Developers
Classifier: Intended Audience :: System Administrators
Classifier: License :: OSI Approved :: MIT License
Classifier: Programming Language :: Python
Classifier: Topic :: Security
Classifier: Topic :: Utilities
Requires-Python: >=3
License-File: LICENSE
License-File: AUTHORS
